house_pricing/__init__.py
house_pricing/ingest_data.py
house_pricing/logger.py
house_pricing/score.py
house_pricing/train.py
Housing_Price_Prediction-0.4.dist-info/LICENSE
Housing_Price_Prediction-0.4.dist-info/METADATA
Housing_Price_Prediction-0.4.dist-info/WHEEL
Housing_Price_Prediction-0.4.dist-info/top_level.txt
Housing_Price_Prediction-0.4.dist-info/RECORD
