Metadata-Version: 2.1
Name: Housing-Price-Prediction
Version: 0.4
Summary: Package for assignment-4.1
Home-page: https://github.com/Parimala01/mle-training
Author: Palle Lakshmi Parimala
Author-email: parimala.palle@tigeranalytics.com
Classifier: Programming Language :: Python :: 3
Classifier: License :: OSI Approved :: MIT License
Classifier: Operating System :: OS Independent
Requires-Python: >=3.6
License-File: LICENSE
